shreddit_cli/__init__.py
shreddit_cli/app.py
shreddit_cli/praw.ini.example
shreddit_cli/shredder.py
shreddit_cli/shreddit.yml.example
shreddit_cli/util.py
shreddit_cli-0.1.0a4.dist-info/METADATA
shreddit_cli-0.1.0a4.dist-info/WHEEL
shreddit_cli-0.1.0a4.dist-info/entry_points.txt
shreddit_cli-0.1.0a4.dist-info/licenses/LICENSE
shreddit_cli-0.1.0a4.dist-info/RECORD
