Metadata-Version: 2.4
Name: shreddit-cli
Version: 0.1.0a4
Summary: Shreddit CLI is a command line tool to automate the removal of reddit posts/comments etc.
Project-URL: Homepage, https://github.com/ashleyconnor/shreddit-cli
Project-URL: Issues, https://github.com/ashleyconnor/shreddit-cli/issues
Author-email: Ashley Connor <me@ashleyconnor.co.uk>, David John <david@vaunt.eu>
License: MIT
License-File: LICENSE
Classifier: Development Status :: 3 - Alpha
Classifier: Environment :: Console
Classifier: Intended Audience :: End Users/Desktop
Classifier: License :: OSI Approved :: MIT License
Classifier: Operating System :: OS Independent
Classifier: Programming Language :: Python :: 3
Requires-Python: >=3.8
Requires-Dist: praw==7.8.1
Requires-Dist: pyyaml==6.0.2
